omuplugin_translator/__init__.py
omuplugin_translator/plugin.py
omuplugin_translator/version.py
omuplugin_translator-0.9.24.dist-info/METADATA
omuplugin_translator-0.9.24.dist-info/WHEEL
omuplugin_translator-0.9.24.dist-info/entry_points.txt
omuplugin_translator-0.9.24.dist-info/RECORD
